django_maven
