Metadata-Version: 1.0
Name: django-maven
Version: 0.2
Summary: Capture exceptions in django management commands into Sentry by Raven
Home-page: https://github.com/saippuakauppias/django-maven
Author: Denis Veselov
Author-email: progr.mail@gmail.com
License: ISC
Keywords: django exception management command sentry raven raise error handling log logging
Platform: UNKNOWN
Classifier: Development Status :: 5 - Production/Stable
Classifier: Framework :: Django
Classifier: Intended Audience :: Developers
Classifier: License :: OSI Approved :: ISC License (ISCL)
Classifier: Operating System :: OS Independent
Classifier: Programming Language :: Python
Classifier: Programming Language :: Python :: 2.6
Classifier: Programming Language :: Python :: 2.7
Classifier: Topic :: Internet :: WWW/HTTP
